optdesign/__init__.py
optdesign-1.0.0.dist-info/licenses/LICENSE.txt
optdesign-1.0.0.dist-info/METADATA
optdesign-1.0.0.dist-info/WHEEL
optdesign-1.0.0.dist-info/top_level.txt
optdesign-1.0.0.dist-info/RECORD
