Metadata-Version: 2.4
Name: optdesign
Version: 1.0.0
Summary: Simple Python implementation of linear optimal design algorithms.
Author-email: Toon Verstraelen <toon.verstraelen@ugent.be>
License-Expression: LGPL-3.0-or-later
Project-URL: Source, https://github.com/molmod/optdesign/
Classifier: Development Status :: 3 - Alpha
Classifier: Environment :: Console
Classifier: Intended Audience :: Education
Classifier: Intended Audience :: Science/Research
Classifier: Operating System :: POSIX :: Linux
Classifier: Operating System :: MacOS
Classifier: Operating System :: Microsoft :: Windows
Classifier: Programming Language :: Python :: 3
Classifier: Programming Language :: Python :: 3 :: Only
Requires-Python: >=3.11
License-File: LICENSE.txt
Requires-Dist: numpy>=1.23.3
Provides-Extra: docs
Requires-Dist: matplotlib>=3.7.0; extra == "docs"
Requires-Dist: jupyter>=1.1.1; extra == "docs"
Requires-Dist: ipykernel>=6.29.5; extra == "docs"
Provides-Extra: tests
Requires-Dist: pytest>=8.4.0; extra == "tests"
Requires-Dist: pytest-rng>=1.0.0; extra == "tests"
Dynamic: license-file
